vap_langchain/__init__.py
vap_langchain/tools.py
vap_langchain-0.2.1.dist-info/METADATA
vap_langchain-0.2.1.dist-info/WHEEL
vap_langchain-0.2.1.dist-info/RECORD
