Metadata-Version: 2.4
Name: vap-langchain
Version: 0.2.1
Summary: VAP LangChain integration - Execution control for agents calling paid APIs
Project-URL: Homepage, https://vapagent.com
Project-URL: Documentation, https://api.vapagent.com/docs
Project-URL: Repository, https://github.com/elestirelbilinc-sketch/vap-showcase
Author-email: VAP Team <hello@vapagent.com>
License-Expression: MIT
Keywords: agents,ai,cost-control,execution-control,langchain,vap
Classifier: Development Status :: 4 - Beta
Classifier: Intended Audience :: Developers
Classifier: License :: OSI Approved :: MIT License
Classifier: Programming Language :: Python :: 3
Classifier: Topic :: Scientific/Engineering :: Artificial Intelligence
Requires-Python: >=3.9
Requires-Dist: langchain-core>=0.1.0
Requires-Dist: vap-sdk>=0.1.0
Provides-Extra: dev
Requires-Dist: pytest; extra == 'dev'
Requires-Dist: pytest-asyncio; extra == 'dev'
